[{"Issue":{"ID":53,"Name":"Problems with defecation","Accuracy":90,"Icd":"K59.0","IcdName":"Constipation","ProfName":"Constipation","Ranking":1},"Specialisation":[{"ID":14,"Name":"Gastroenterology","SpecialistID":40},{"ID":15,"Name":"General practice","SpecialistID":3},{"ID":19,"Name":"Internal medicine","SpecialistID":4}]},{"Issue":{"ID":495,"Name":"Bloated belly","Accuracy":80.99999,"Icd":"R14","IcdName":"Flatulence and related conditions","ProfName":"Meteorism","Ranking":2},"Specialisation":[{"ID":15,"Name":"General practice","SpecialistID":3}]},{"Issue":{"ID":472,"Name":"Stomach irritation","Accuracy":75.375,"Icd":"K30","IcdName":"Functional dyspepsia","ProfName":"Functional dyspepsia","Ranking":3},"Specialisation":[{"ID":14,"Name":"Gastroenterology","SpecialistID":40},{"ID":15,"Name":"General practice","SpecialistID":3}]},{"Issue":{"ID":475,"Name":"Eating disorder","Accuracy":22.5,"Icd":"F50","IcdName":"Eating disorders","ProfName":"Psychogenic eating disorders","Ranking":4},"Specialisation":[{"ID":15,"Name":"General practice","SpecialistID":3},{"ID":36,"Name":"Psychiatry","SpecialistID":62}]},{"Issue":{"ID":193,"Name":"Fluid accumulation in the abdomen","Accuracy":11.25,"Icd":"R18","IcdName":"Ascites","ProfName":"Ascites","Ranking":5},"Specialisation":[{"ID":15,"Name":"General practice","SpecialistID":3},{"ID":19,"Name":"Internal medicine","SpecialistID":4}]},{"Issue":{"ID":130,"Name":"Abdominal hernia","Accuracy":9.45,"Icd":"K40;K41;K42;K43;K44;K45;K46","IcdName":"Inguinal hernia;Femoral hernia;Umbilical hernia;Ventral hernia;Diaphragmatic hernia;Other abdominal hernia;Unspecified abdominal hernia","ProfName":"Abdominal wall hernia","Ranking":6},"Specialisation":[{"ID":15,"Name":"General practice","SpecialistID":3},{"ID":39,"Name":"Surgery","SpecialistID":13}]}]