[{"Issue":{"ID":329,"Name":"Water accumulation in the tissues","Accuracy":90,"Icd":"R60.9","IcdName":"Oedema, unspecified","ProfName":"Edema","Ranking":1},"Specialisation":[{"ID":15,"Name":"General practice","SpecialistID":3},{"ID":19,"Name":"Internal medicine","SpecialistID":4}]},{"Issue":{"ID":91,"Name":"Enlarged and twisted veins","Accuracy":67.5,"Icd":"I83","IcdName":"Varicose veins of lower extremities","ProfName":"Varicose veins","Ranking":2},"Specialisation":[{"ID":7,"Name":"Angiology","SpecialistID":17},{"ID":15,"Name":"General practice","SpecialistID":3},{"ID":39,"Name":"Surgery","SpecialistID":13}]},{"Issue":{"ID":210,"Name":"Chronic vein insufficiency","Accuracy":55.125,"Icd":"I87.2","IcdName":"Venous insufficiency (chronic)(peripheral)","ProfName":"Chronic venous insufficiency","Ranking":3},"Specialisation":[{"ID":7,"Name":"Angiology","SpecialistID":17},{"ID":11,"Name":"Dermatology","SpecialistID":22},{"ID":15,"Name":"General practice","SpecialistID":3}]},{"Issue":{"ID":122,"Name":"Inflammation of veins","Accuracy":33.75,"Icd":"I80","IcdName":"Phlebitis and thrombophlebitis","ProfName":"Phlebitis","Ranking":4},"Specialisation":[{"ID":7,"Name":"Angiology","SpecialistID":17},{"ID":15,"Name":"General practice","SpecialistID":3},{"ID":19,"Name":"Internal medicine","SpecialistID":4}]},{"Issue":{"ID":92,"Name":"Clot in a vein","Accuracy":14.0625,"Icd":"I80.2","IcdName":"Phlebitis and thrombophlebitis of other deep vessels of lower extremities","ProfName":"Deep vein thrombosis","Ranking":5},"Specialisation":[{"ID":7,"Name":"Angiology","SpecialistID":17},{"ID":15,"Name":"General practice","SpecialistID":3},{"ID":19,"Name":"Internal medicine","SpecialistID":4}]}]